Metadata-Version: 1.1
Name: yaz0
Version: 0.1.0
Summary: Python module for decompressing Nintendo Yaz0 data.
Home-page: https://github.com/Syroot/yaz0
Author: Syroot
Author-email: dev@syroot.com
License: MIT
Download-URL: https://github.com/Syroot/yaz0/archive/0.1.0.tar.gz
Platform: UNKNOWN
